spectcl/__init__.py
spectcl/apps/__init__.py
spectcl/apps/viz/__init__.py
spectcl/apps/viz/app.py
spectcl/apps/viz/ui/__init__.py
spectcl/apps/viz/ui/ui_app.py
spectcl/client/__init__.py
spectcl/contrib/__init__.py
spectcl/contrib/data.py
spectcl/contrib/template.json
spectcl/data/__init__.py
spectcl/data/action.toml
spectcl/data/client.py
spectcl/data/gate.py
spectcl/data/plot.py
spectcl/data/spectrum.py
spectcl/data/stats.py
spectcl/data/utils.py
pyspectcl-0.4.2.dist-info/LICENSE
pyspectcl-0.4.2.dist-info/METADATA
pyspectcl-0.4.2.dist-info/WHEEL
pyspectcl-0.4.2.dist-info/entry_points.txt
pyspectcl-0.4.2.dist-info/top_level.txt
pyspectcl-0.4.2.dist-info/RECORD
